{
  "type_description_msg": {
    "type_description": {
      "type_name": "person_msgs/srv/Query_Request",
      "fields": [
        {
          "name": "name",
          "type": {
            "type_id": 17,
            "capacity": 0,
            "string_capacity": 0,
            "nested_type_name": ""
          },
          "default_value": ""
        }
      ]
    },
    "referenced_type_descriptions": []
  },
  "type_hashes": [
    {
      "type_name": "person_msgs/srv/Query_Request",
      "hash_string": "RIHS01_900d2fd481a9da0a75a56e8fb803ff2a9f9c653eda68cb438141ab9a83bab922"
    }
  ]
}